snagit/__init__.py
snagit/__main__.py
snagit/core.py
snagit/exceptions.py
snagit/repl.py
snagit/utils.py
snagit/lib/__init__.py
snagit/lib/base.py
snagit/lib/lines.py
snagit/lib/soup.py
snagit/lib/text.py
snagit-0.3.0.dist-info/DESCRIPTION.rst
snagit-0.3.0.dist-info/METADATA
snagit-0.3.0.dist-info/RECORD
snagit-0.3.0.dist-info/WHEEL
snagit-0.3.0.dist-info/entry_points.txt
snagit-0.3.0.dist-info/metadata.json
snagit-0.3.0.dist-info/top_level.txt
