Metadata-Version: 2.0
Name: snagit
Version: 0.3.0
Summary: Simple tools for downloading, cleaning, extracting and parsing content
Home-page: https://github.com/dakrauth/snagit
Author: David A Krauth
Author-email: dakrauth@gmail.com
License: MIT License
Platform: any
Classifier: Environment :: Web Environment
Classifier: Framework :: Django
Classifier: License :: OSI Approved :: MIT License
Classifier: Programming Language :: Python
Classifier: Programming Language :: Python :: 2
Classifier: Programming Language :: Python :: 2.7
Requires-Dist: requests
Requires-Dist: beautifulsoup4
Requires-Dist: strutil
